[{"name ":"Greer Gadson","age":89},
{"name ":"Addie Phoenix","age":84},
{"name ":"Amalia Mathet","age":48},
{"name ":"Derby Looker","age":41},
{"name ":"Tommie Cavanagh","age":19},
{"name ":"Gayelord Hurren","age":34},
{"name ":"Kellby Fidgin","age":85},
{"name ":"Jandy Frankel","age":22},
{"name ":"Jose Rossborough","age":79},
{"name ":"Cassaundra Perroni","age":27},
{"name ":"Fabian Petrecz","age":80},
{"name ":"Myca Woodbridge","age":70},
{"name ":"Tadio Allcock","age":34},
{"name ":"Enrika McGarrell","age":68},
{"name ":"Magnum Coatman","age":90},
{"name ":"Paco Elner","age":29},
{"name ":"Aleksandr Carder","age":75},
{"name ":"Mitchael Dorrell","age":43},
{"name ":"Meggie Yakubov","age":35},
{"name ":"Prisca Petrolli","age":47},
{"name ":"Kara-lynn Skydall","age":60},
{"name ":"Vita Pegrum","age":54},
{"name ":"Torre Rolph","age":25},
{"name ":"Perle Terrington","age":68},
{"name ":"Winfield Alcido","age":86},
{"name ":"Jenni Bes","age":81},
{"name ":"Katya Boddis","age":28},
{"name ":"Enrika Woodberry","age":83},
{"name ":"Seka Renbold","age":52},
{"name ":"Magnum Mellmoth","age":63},
{"name ":"Winona Rodenburgh","age":58},
{"name ":"Mei Leathley","age":53},
{"name ":"Sheeree Ind","age":35},
{"name ":"Tiena McCallam","age":39},
{"name ":"Miranda Dunabie","age":47},
{"name ":"Mike Anfossi","age":21},
{"name ":"Windy Briggdale","age":52},
{"name ":"Igor Bredee","age":33},
{"name ":"Dulcine Kipling","age":34},
{"name ":"Dorothy McGillivray","age":69},
{"name ":"Isak Salvidge","age":82},
{"name ":"Evvy Cant","age":38},
{"name ":"Deanne Oattes","age":89},
{"name ":"Antonetta Geffe","age":73},
{"name ":"Jobye Blunt","age":90},
{"name ":"Stacy Calbrathe","age":96},
{"name ":"Lynsey Marcroft","age":39},
{"name ":"Billy Van Vuuren","age":90},
{"name ":"Alaine Erb","age":50},
{"name ":"Malena Shave","age":94},
{"name ":"Gearalt Bonnette","age":40},
{"name ":"Clair D'Elia","age":91},
{"name ":"Appolonia Biffen","age":65},
{"name ":"Romonda Beveridge","age":70},
{"name ":"Dennie Schulke","age":84},
{"name ":"Cindelyn Massow","age":50},
{"name ":"Mia Reynard","age":48},
{"name ":"Katey Renison","age":72},
{"name ":"Cleopatra Eastman","age":42},
{"name ":"Diana Pattington","age":29},
{"name ":"Randy Alliker","age":95},
{"name ":"Sherwood Paolacci","age":84},
{"name ":"Corette Ivshin","age":63},
{"name ":"Whit MacRonald","age":23},
{"name ":"Glynda Posner","age":86},
{"name ":"Cal Bickford","age":37},
{"name ":"Nicolea Krates","age":50},
{"name ":"Shana Lorne","age":18},
{"name ":"Celia Jordine","age":45},
{"name ":"Sidonnie Weldrick","age":52},
{"name ":"Elbert Hacksby","age":30},
{"name ":"Con Ianinotti","age":94},
{"name ":"Booth Mawby","age":42},
{"name ":"Tildi Burnip","age":63},
{"name ":"Thom Komorowski","age":55},
{"name ":"Raffaello Kurton","age":93},
{"name ":"Flossie Hanwright","age":96},
{"name ":"Ava Filipyev","age":97},
{"name ":"Kin Robben","age":60},
{"name ":"Chrysler Grzeszczyk","age":49},
{"name ":"Kelly Aymer","age":83},
{"name ":"Marijo Kunkler","age":44},
{"name ":"Roxine Fishbourne","age":19},
{"name ":"Rufe Fortune","age":27},
{"name ":"Brigitta Van der Hoeven","age":85},
{"name ":"Kassia Cyples","age":48},
{"name ":"Frasco Cunio","age":81},
{"name ":"Flory Jerred","age":73},
{"name ":"Angie Acott","age":38},
{"name ":"Elberta Attoe","age":34},
{"name ":"Norrie Gainfort","age":99},
{"name ":"Katha Macbane","age":44},
{"name ":"Avrit Forster","age":49},
{"name ":"Cristobal Whyborn","age":36},
{"name ":"Sibella Domone","age":82},
{"name ":"Adamo Adamini","age":71},
{"name ":"Micah Hetterich","age":84},
{"name ":"Jasmina Obern","age":83},
{"name ":"Felicdad Raison","age":86},
{"name ":"Geneva Coulling","age":60},
{"name ":"Lockwood Clemow","age":47},
{"name ":"Marco Crookshanks","age":89},
{"name ":"Diego Holt","age":57},
{"name ":"Tomlin Wallworke","age":24},
{"name ":"Pancho Esbrook","age":41},
{"name ":"Alva Fydo","age":86},
{"name ":"Harriette Merritt","age":52},
{"name ":"Afton Edgeson","age":80},
{"name ":"Renaldo Langfat","age":85},
{"name ":"Elsa Goodenough","age":49},
{"name ":"Kirby Belham","age":48},
{"name ":"Drucy Kilcullen","age":56},
{"name ":"Zeke Boissier","age":86},
{"name ":"Humfried Napton","age":100},
{"name ":"Kristen Cansdale","age":67},
{"name ":"Jessica McPeeters","age":41},
{"name ":"Dayle Julien","age":50},
{"name ":"Chadd Iacopo","age":87},
{"name ":"Aimee Offield","age":69},
{"name ":"Burnard Pilling","age":78},
{"name ":"Meriel Coneybeer","age":89},
{"name ":"Mercie McGurn","age":90},
{"name ":"Peta Gornal","age":74},
{"name ":"Adams Collins","age":54},
{"name ":"Roobbie Esche","age":34},
{"name ":"Elmer McCormick","age":96},
{"name ":"Issi Merriman","age":19},
{"name ":"Bale Benns","age":29},
{"name ":"Dorisa Heskin","age":71},
{"name ":"Timmie Woodburn","age":21},
{"name ":"Nelly Puttnam","age":84},
{"name ":"Brena Twyford","age":92},
{"name ":"Elysia McEntee","age":71},
{"name ":"Geno Carlin","age":21},
{"name ":"Dion Hegel","age":54},
{"name ":"Arnold Perassi","age":83},
{"name ":"Allen Lissandrini","age":93},
{"name ":"Brian Darthe","age":55},
{"name ":"Seymour Romi","age":37},
{"name ":"Johnnie Pentecust","age":71},
{"name ":"Kayley Branigan","age":45},
{"name ":"Domenico Skipworth","age":91},
{"name ":"Clay Varrow","age":69},
{"name ":"Adams Perrycost","age":47},
{"name ":"Dorri Turpin","age":53},
{"name ":"Gillie Swafford","age":47},
{"name ":"Shoshanna Dodshun","age":80},
{"name ":"Andeee Ewing","age":30},
{"name ":"Ario Parmiter","age":42},
{"name ":"Margarethe Kippie","age":75},
{"name ":"Raphael Wivell","age":79},
{"name ":"Robby Northbridge","age":41},
{"name ":"Caleb Van Der Hoog","age":69},
{"name ":"Charlotta Soutar","age":71},
{"name ":"Friedrich MacAndreis","age":52},
{"name ":"Candi Renzullo","age":31},
{"name ":"Carmine Toffolo","age":44},
{"name ":"Sofie McGeffen","age":58},
{"name ":"Reinaldos Ruffle","age":62},
{"name ":"Webb Moretto","age":73},
{"name ":"Delaney Calderhead","age":61},
{"name ":"Judd Arlett","age":72},
{"name ":"Evie Unthank","age":18},
{"name ":"Dorri Balffye","age":87},
{"name ":"Carmelle Shewan","age":45},
{"name ":"Cchaddie De Beauchamp","age":49},
{"name ":"Lacie Clendennen","age":26},
{"name ":"Gerard Peery","age":28},
{"name ":"Gardiner Stote","age":89},
{"name ":"Brittni Hedditch","age":25},
{"name ":"Blondie Bloor","age":60},
{"name ":"Dyan Edgin","age":69},
{"name ":"Jami Suter","age":99},
{"name ":"Alidia Gotling","age":54},
{"name ":"Iona Bontine","age":59},
{"name ":"Jolyn Shireff","age":98},
{"name ":"Fax Belvard","age":23},
{"name ":"Aggi Malden","age":21},
{"name ":"Kiah Howorth","age":80},
{"name ":"Gwen Dun","age":56},
{"name ":"Tracee Glavias","age":51},
{"name ":"Even Durrand","age":28},
{"name ":"Caesar Hendrikse","age":67},
{"name ":"Harriet Collingworth","age":33},
{"name ":"Micki Woodhouse","age":78},
{"name ":"Henka Kimbly","age":40},
{"name ":"Carlene Biddell","age":80},
{"name ":"Marcos Teague","age":20},
{"name ":"Nydia True","age":100},
{"name ":"Otha Mallaby","age":40},
{"name ":"Rupert Willishire","age":34},
{"name ":"Anett Ogglebie","age":80},
{"name ":"Basilius Lillecrop","age":47},
{"name ":"Debbi Varley","age":34},
{"name ":"Zabrina Pappin","age":68},
{"name ":"Pennie Degoix","age":56},
{"name ":"Filberto Meriott","age":75},
{"name ":"Petunia Dobbie","age":82},
{"name ":"Lloyd Casford","age":56},
{"name ":"Christoforo Sommerscales","age":66},
{"name ":"Floria Semerad","age":68},
{"name ":"Bowie Petett","age":70},
{"name ":"Lonny Shorthill","age":30},
{"name ":"Steve Sugg","age":27},
{"name ":"Merry Bye","age":93},
{"name ":"Dalt Brou","age":71},
{"name ":"Dion Klampk","age":23},
{"name ":"Frazier Gullivent","age":97},
{"name ":"Lilly Sepey","age":71},
{"name ":"Steffen Sitlington","age":26},
{"name ":"Gaven Stirling","age":85},
{"name ":"Allina Llywarch","age":85},
{"name ":"Forster Spellecy","age":48},
{"name ":"Brena Winstone","age":61},
{"name ":"Brittani Maundrell","age":52},
{"name ":"Karlens Izsak","age":59},
{"name ":"Dinny Marxsen","age":93},
{"name ":"Beatrice Rosel","age":28},
{"name ":"Evelyn Rubke","age":66},
{"name ":"Elaina Pymer","age":42},
{"name ":"Maryann Pabel","age":24},
{"name ":"Annamarie Ringwood","age":37},
{"name ":"Alisa Gargett","age":100},
{"name ":"Darci Quincee","age":39},
{"name ":"Annaliese Beinisch","age":38},
{"name ":"Audy Crisall","age":53},
{"name ":"Dorella Dottridge","age":45},
{"name ":"Manon Hellyar","age":77},
{"name ":"Joellyn Minker","age":49},
{"name ":"Karrah Lunn","age":47},
{"name ":"Felipa Gresch","age":75},
{"name ":"Ogdan Wethers","age":74},
{"name ":"Malynda Antognazzi","age":42},
{"name ":"Richie Clamp","age":91},
{"name ":"Elvira Seiler","age":95},
{"name ":"Rice MacKenney","age":30},
{"name ":"Janaya Aspital","age":32},
{"name ":"Gayelord Sindell","age":37},
{"name ":"Darnell Ferrers","age":86},
{"name ":"Bernita Ramage","age":41},
{"name ":"Joe Strauss","age":86},
{"name ":"Addia Peschet","age":56},
{"name ":"Noel Le feuvre","age":42},
{"name ":"Eachelle Onions","age":56},
{"name ":"Eulalie Ranken","age":65},
{"name ":"Tristan MacNair","age":43},
{"name ":"Derrick Slatter","age":62},
{"name ":"Antonio Kisting","age":100},
{"name ":"Brew Shoesmith","age":27},
{"name ":"Gary Merner","age":100},
{"name ":"Heddie Bento","age":69},
{"name ":"Merrill Fridaye","age":36},
{"name ":"Charity Spatoni","age":38},
{"name ":"Bonny Flint","age":75},
{"name ":"Binnie Ashton","age":49},
{"name ":"Nicolis Anderson","age":62},
{"name ":"Harris McDirmid","age":54},
{"name ":"Alexa d' Elboux","age":57},
{"name ":"Othella Dallyn","age":32},
{"name ":"Addia Sales","age":50},
{"name ":"Kerwinn Deakin","age":37},
{"name ":"Padget Gianneschi","age":18},
{"name ":"Gracie Doiley","age":61},
{"name ":"Florian Allery","age":30},
{"name ":"Jocko Folbigg","age":23},
{"name ":"Carine Brookhouse","age":28},
{"name ":"Prudence Gentsch","age":57},
{"name ":"Celinda Tomasini","age":30},
{"name ":"Manda Jerratsch","age":70},
{"name ":"Mahala Leyre","age":26},
{"name ":"Matilda Ahern","age":99},
{"name ":"Joete Dugan","age":81},
{"name ":"Fergus Letrange","age":23},
{"name ":"Jocelyne Kasper","age":47},
{"name ":"Wenona Kirvell","age":22},
{"name ":"Benjie Palphreyman","age":65},
{"name ":"Dannel Norgate","age":78},
{"name ":"Boonie Pendered","age":70},
{"name ":"Storm Fenne","age":44},
{"name ":"Creighton Lippett","age":35},
{"name ":"Yves Hancock","age":54},
{"name ":"Athene Nockles","age":70},
{"name ":"Maure Rolingson","age":61},
{"name ":"Hedy Halgarth","age":28},
{"name ":"Randy Laugheran","age":20},
{"name ":"Sacha Woodroffe","age":50},
{"name ":"Clint Appleford","age":20},
{"name ":"Peria Ghelardoni","age":24},
{"name ":"Currey Haggerty","age":35},
{"name ":"Alidia Woodage","age":83},
{"name ":"Christa MacGuffie","age":30},
{"name ":"Odele Iacofo","age":51},
{"name ":"Wallis Durbin","age":76},
{"name ":"Marilin Rustidge","age":96},
{"name ":"Dayle Edgeson","age":44},
{"name ":"Maurine Keneforde","age":25},
{"name ":"Cassie Osmond","age":39},
{"name ":"Hughie Harragin","age":72},
{"name ":"Ebonee Julien","age":96},
{"name ":"Anneliese Rosenbarg","age":46},
{"name ":"Milena Hedderly","age":51},
{"name ":"Ginni Duddin","age":29},
{"name ":"Clevey Rumbellow","age":64},
{"name ":"Hamid Branchflower","age":25},
{"name ":"Archibold Dukelow","age":59},
{"name ":"Preston Josephson","age":42},
{"name ":"Pauletta Scrimshaw","age":33},
{"name ":"Artus Moodie","age":89},
{"name ":"Carroll Keme","age":70},
{"name ":"Courtney Burleigh","age":84},
{"name ":"Amelia Mordey","age":98},
{"name ":"Pietrek Owen","age":44},
{"name ":"Clevey Bulluck","age":89},
{"name ":"Ian Dunlap","age":40},
{"name ":"Elsi Jessen","age":43},
{"name ":"Imogen Bestwall","age":57},
{"name ":"Yoshiko Gresswell","age":39},
{"name ":"Noak Harken","age":33},
{"name ":"Thain Randalson","age":69},
{"name ":"Sabine Bradnum","age":29},
{"name ":"Yard Klosa","age":22},
{"name ":"Erik State","age":81},
{"name ":"Lenna Hallwood","age":46},
{"name ":"Mara Di Roberto","age":79},
{"name ":"Cyril Dearlove","age":90},
{"name ":"Fraser Snelle","age":35},
{"name ":"Astrix Pesak","age":76},
{"name ":"Theodor Ruoff","age":72},
{"name ":"Reece Peschet","age":32},
{"name ":"Georgianne Mobley","age":81},
{"name ":"Lorenza Rainsden","age":93},
{"name ":"Rockie O'Doherty","age":67},
{"name ":"Edgardo Quilliam","age":79},
{"name ":"Othilie Chiswell","age":33},
{"name ":"Jenelle Pietzke","age":35},
{"name ":"Manda Dobbings","age":65},
{"name ":"Willette Cantillion","age":63},
{"name ":"Truman Madelin","age":45},
{"name ":"Malva Ismead","age":99},
{"name ":"Jessy Conville","age":81},
{"name ":"Christopher Greenleaf","age":38},
{"name ":"Hansiain Lill","age":87},
{"name ":"Eyde Meakes","age":31},
{"name ":"Ozzie Grinyov","age":58},
{"name ":"Amity Davley","age":75},
{"name ":"Billie Gianinotti","age":86},
{"name ":"Kerrie Patriskson","age":58},
{"name ":"Ellie Ganforthe","age":91},
{"name ":"Matthaeus Coneau","age":36},
{"name ":"Garrik MacMeeking","age":46},
{"name ":"Shaylynn Issatt","age":31},
{"name ":"Gavra Sellner","age":40},
{"name ":"Archie Boocock","age":85},
{"name ":"Cybill Corroyer","age":61},
{"name ":"Filip Silk","age":96},
{"name ":"Thain Despenser","age":53},
{"name ":"Bobbee Ivashinnikov","age":59},
{"name ":"Rafael Saurat","age":19},
{"name ":"Randy Corragan","age":19},
{"name ":"Anitra Bellfield","age":97},
{"name ":"Colas Bowra","age":37},
{"name ":"Ilka McLernon","age":57},
{"name ":"Andy Pettegre","age":52},
{"name ":"Aggie Hastin","age":28},
{"name ":"Cristie Hynam","age":86},
{"name ":"Arnold Enevold","age":18},
{"name ":"Vinson Dumbrill","age":78},
{"name ":"Evin Reimer","age":62},
{"name ":"Kippy Sindall","age":75},
{"name ":"Berni Eldin","age":76},
{"name ":"Amelie Zealander","age":55},
{"name ":"Ches Scading","age":36},
{"name ":"Randolf Dewdney","age":89},
{"name ":"Violet Reame","age":99},
{"name ":"Caitlin Tetther","age":93},
{"name ":"Jamie Leonida","age":43},
{"name ":"Fair Minogue","age":37},
{"name ":"Clevie Flament","age":64},
{"name ":"Ellette Gopsall","age":83},
{"name ":"Goldi Jessel","age":28},
{"name ":"Halsy Alsop","age":27},
{"name ":"Linus Wanne","age":25},
{"name ":"Hermine Sopper","age":33},
{"name ":"Glynis Goodhay","age":77},
{"name ":"Lissy Gunningham","age":75},
{"name ":"Pooh Swabey","age":49},
{"name ":"Adora Antognazzi","age":65},
{"name ":"Rodney Andrysiak","age":34},
{"name ":"Kevon Egel","age":78},
{"name ":"Thomasa Roncelli","age":80},
{"name ":"Fayth Trotman","age":25},
{"name ":"Giulietta Burren","age":23},
{"name ":"Lind Glasebrook","age":18},
{"name ":"Althea Cuncliffe","age":47},
{"name ":"Oralia Harborow","age":90},
{"name ":"Alford Thurling","age":94},
{"name ":"Erek Gouth","age":25},
{"name ":"Guss Bompas","age":78},
{"name ":"Morlee Mickleborough","age":67},
{"name ":"Cosetta Yole","age":90},
{"name ":"Cristy Swigger","age":30},
{"name ":"Tim Yanshinov","age":55},
{"name ":"Maybelle Reay","age":90},
{"name ":"Emogene Dimmne","age":64},
{"name ":"Laina Yegorkov","age":82},
{"name ":"Roby Duding","age":100},
{"name ":"Mendel Batiste","age":61},
{"name ":"Glen Blamires","age":60},
{"name ":"Loraine Brearton","age":82},
{"name ":"Portie Stolz","age":58},
{"name ":"Corby Stirley","age":75},
{"name ":"Esme Gonnet","age":26},
{"name ":"Hughie Pile","age":33},
{"name ":"Marvin Imesson","age":56},
{"name ":"Hayward O'Doogan","age":38},
{"name ":"Emmett Waszkiewicz","age":84},
{"name ":"Boigie Thornbarrow","age":67},
{"name ":"Christian Townsend","age":51},
{"name ":"Dayle Jay","age":36},
{"name ":"Spike Lorkins","age":82},
{"name ":"Putnam Croston","age":35},
{"name ":"Umeko Trase","age":55},
{"name ":"Josi Harker","age":64},
{"name ":"Boone Shurey","age":33},
{"name ":"Sollie Rosencwaig","age":47},
{"name ":"Lothaire Eggins","age":38},
{"name ":"Violet Every","age":76},
{"name ":"Natassia Balas","age":58},
{"name ":"Delly Bouchard","age":72},
{"name ":"Annabella Eisig","age":42},
{"name ":"Francisca Sandys","age":65},
{"name ":"Norma Caso","age":90},
{"name ":"Catherin Albisser","age":27},
{"name ":"Cicely Wattinham","age":57},
{"name ":"Averell Marzele","age":90},
{"name ":"Renee McKeowon","age":70},
{"name ":"Carter Arnao","age":86},
{"name ":"Lonee Rousel","age":84},
{"name ":"Free Auty","age":40},
{"name ":"Anna-diana Walbrun","age":86},
{"name ":"Robin Garber","age":61},
{"name ":"Link Poundsford","age":56},
{"name ":"Norah Gartsyde","age":63},
{"name ":"Dorine Romanet","age":82},
{"name ":"Leanor Scirman","age":49},
{"name ":"Colas Eddowes","age":54},
{"name ":"Brandea Sor","age":76},
{"name ":"Christy Bert","age":32},
{"name ":"Alfonse Deinert","age":38},
{"name ":"Rand Mullineux","age":41},
{"name ":"Montgomery Gamble","age":31},
{"name ":"Alaster Muncie","age":42},
{"name ":"Vittorio Marriner","age":47},
{"name ":"Rodolph Conkay","age":21},
{"name ":"Thorstein Shortall","age":88},
{"name ":"Paloma Hayselden","age":78},
{"name ":"Jule Hardey","age":61},
{"name ":"Milty Pickrell","age":56},
{"name ":"Renie Lowers","age":49},
{"name ":"Caron Mitcheson","age":56},
{"name ":"Flor Christofol","age":59},
{"name ":"Sarge Janic","age":45},
{"name ":"Loutitia Neads","age":26},
{"name ":"Thomasine Cullen","age":19},
{"name ":"Chick Handscomb","age":20},
{"name ":"Carol-jean Jeaycock","age":86},
{"name ":"Dimitry Godwin","age":50},
{"name ":"Eran Maycock","age":44},
{"name ":"Kellyann Pymar","age":100},
{"name ":"Fitzgerald Hebborne","age":72},
{"name ":"Jaquith Dunmore","age":30},
{"name ":"Alvis Ainslee","age":54},
{"name ":"Rayshell de Quincey","age":49},
{"name ":"Connor Compford","age":70},
{"name ":"Diannne Kersey","age":69},
{"name ":"Gwyneth De Few","age":36},
{"name ":"Kristan Sargent","age":52},
{"name ":"Oralle McTrustie","age":36},
{"name ":"Normy Southwood","age":20},
{"name ":"Angelo Feek","age":26},
{"name ":"Galven Hiers","age":39},
{"name ":"Kellie Fulk","age":75},
{"name ":"Vilhelmina Casaroli","age":87},
{"name ":"Vladimir Jillard","age":31},
{"name ":"Bondie MacKellar","age":79},
{"name ":"Thibaud Wileman","age":26},
{"name ":"Dane Gillicuddy","age":20},
{"name ":"Maribelle Napper","age":30},
{"name ":"Gearard Drackford","age":97},
{"name ":"Rasia Torvey","age":20},
{"name ":"Kariotta O'Hartnett","age":80},
{"name ":"Sutherland Tichner","age":68},
{"name ":"Tommie Leighton","age":78},
{"name ":"Nissie Sharpless","age":73},
{"name ":"Bartholemy McGinnis","age":61},
{"name ":"Allayne Whitbread","age":92},
{"name ":"Teddy Oldcote","age":88},
{"name ":"Cross Stiffkins","age":74},
{"name ":"Janelle Dreger","age":85},
{"name ":"Reyna Andreou","age":52},
{"name ":"Melodee Brendeke","age":72},
{"name ":"Davie Scarse","age":30},
{"name ":"Rurik Gowrie","age":47},
{"name ":"Eldridge Wensley","age":27},
{"name ":"Sherman Liggins","age":21},
{"name ":"Tiffani Heam","age":61},
{"name ":"Rudy Adshede","age":77},
{"name ":"Rodi Twelves","age":73},
{"name ":"Corney Chalcraft","age":54},
{"name ":"Georgette Dyhouse","age":21},
{"name ":"Silvain Pooke","age":39},
{"name ":"Dom Rubury","age":91},
{"name ":"Meriel Haseley","age":56},
{"name ":"Otis Frayne","age":37},
{"name ":"Kyle Patnelli","age":69},
{"name ":"Aluin Ortiga","age":94},
{"name ":"Lancelot O Sullivan","age":79},
{"name ":"Dede Kubiczek","age":45},
{"name ":"Filia Chipchase","age":72},
{"name ":"Daryn Pearde","age":99},
{"name ":"Josefa Drinkhill","age":38},
{"name ":"Elspeth Meenan","age":31},
{"name ":"Clovis Georgeon","age":53},
{"name ":"Abel Dring","age":89},
{"name ":"Edlin Claire","age":83},
{"name ":"Tye Gehring","age":77},
{"name ":"Sargent Folini","age":71},
{"name ":"Terri Threadgold","age":62},
{"name ":"Sinclare Govan","age":85},
{"name ":"Jeremiah Braban","age":48},
{"name ":"Alvie Coultas","age":27},
{"name ":"Salvador Steely","age":39},
{"name ":"Fredrika Beatty","age":69},
{"name ":"Tiena Woodfine","age":96},
{"name ":"Blair Baford","age":53},
{"name ":"Ewen Alejandro","age":31},
{"name ":"Steffen Dytham","age":98},
{"name ":"Barry Gouldstone","age":20},
{"name ":"Ernesta Boij","age":35},
{"name ":"Garrek GiacobbiniJacob","age":84},
{"name ":"Clarissa Cropton","age":84},
{"name ":"Donall Slite","age":78},
{"name ":"Urbano Brade","age":41},
{"name ":"Merrielle Schruyer","age":35},
{"name ":"Gusta Di Ruggiero","age":95},
{"name ":"Nikolas Cansfield","age":22},
{"name ":"Leonie Marte","age":88},
{"name ":"Kliment Purrier","age":51},
{"name ":"Mirelle Bartoszinski","age":69},
{"name ":"Arel Eplate","age":97},
{"name ":"Annmarie Drewet","age":93},
{"name ":"Gloriane Davall","age":25},
{"name ":"Jerrome Carss","age":82},
{"name ":"Donna Hobden","age":72},
{"name ":"Obadias Torre","age":32},
{"name ":"Abbye Ourtic","age":91},
{"name ":"Travus Neiland","age":76},
{"name ":"Lezlie Treffrey","age":97},
{"name ":"Marylin Scurrah","age":38},
{"name ":"Tessy Tremolieres","age":39},
{"name ":"Ede Unstead","age":70},
{"name ":"Jaimie Dumphry","age":80},
{"name ":"Cairistiona Smithe","age":89},
{"name ":"Gregoor Benedetti","age":79},
{"name ":"Tillie Rafferty","age":25},
{"name ":"Arabelle MacColl","age":39},
{"name ":"Flynn Bletsoe","age":42},
{"name ":"Merci Rotherforth","age":97},
{"name ":"Gherardo Haulkham","age":39},
{"name ":"Greggory Statersfield","age":46},
{"name ":"Trixy Legrice","age":69},
{"name ":"Barde Crawcour","age":69},
{"name ":"Niels Phelipeaux","age":82},
{"name ":"Margy Beebis","age":71},
{"name ":"Faina Shepcutt","age":89},
{"name ":"Elisha Squirrell","age":60},
{"name ":"Nataline Heinrici","age":68},
{"name ":"Emmit Zecchinii","age":40},
{"name ":"Nowell Tirte","age":50},
{"name ":"Laurie Spray","age":87},
{"name ":"Delora Bartalin","age":37},
{"name ":"Albina Lasslett","age":48},
{"name ":"Jacki Benettini","age":98},
{"name ":"Webster Jarratt","age":32},
{"name ":"Arri Ridler","age":74},
{"name ":"Ben Emps","age":28},
{"name ":"Napoleon Scholtz","age":38},
{"name ":"Skell Danihelka","age":37},
{"name ":"Verina Rathmell","age":79},
{"name ":"Orbadiah Deetlefs","age":23},
{"name ":"Gherardo Merrilees","age":38},
{"name ":"Fiona Van der Baaren","age":47},
{"name ":"Noell McIsaac","age":62},
{"name ":"Kendre Burner","age":56},
{"name ":"Robinetta Covotto","age":81},
{"name ":"Thornie Lymer","age":45},
{"name ":"Alano Duiged","age":92},
{"name ":"Lucita Morcom","age":79},
{"name ":"Ursala Clampe","age":92},
{"name ":"Tasia Ondrousek","age":64}]